{
	"name": "tblsnidbrbillsplitDupsellout",
	"properties": {
		"linkedServiceName": {
			"referenceName": "DataFoundationDB",
			"type": "LinkedServiceReference"
		},
		"folder": {
			"name": "DF_DBConnection/LEAP Tables"
		},
		"annotations": [],
		"type": "AzureSqlDWTable",
		"schema": [
			{
				"name": "BranchSubDNodeID",
				"type": "int",
				"precision": 10
			},
			{
				"name": "RptMOnthYear",
				"type": "int",
				"precision": 10
			},
			{
				"name": "TrnDate",
				"type": "date"
			},
			{
				"name": "StoreID",
				"type": "int",
				"precision": 10
			},
			{
				"name": "SalesValue",
				"type": "decimal",
				"precision": 18,
				"scale": 2
			},
			{
				"name": "BranchName",
				"type": "varchar"
			},
			{
				"name": "MonthYear",
				"type": "varchar"
			},
			{
				"name": "StoreName",
				"type": "varchar"
			},
			{
				"name": "flgRF",
				"type": "tinyint",
				"precision": 3
			},
			{
				"name": "SellerType",
				"type": "varchar"
			},
			{
				"name": "DistributorName",
				"type": "varchar"
			},
			{
				"name": "SiteName",
				"type": "varchar"
			}
		],
		"typeProperties": {
			"schema": "dbo",
			"table": "tblSniDbrBillSplitDupSellout"
		}
	}
}