{
	"$schema": "http://schema.management.azure.com/schemas/2015-01-01/deploymentTemplate.json#",
	"contentVersion": "1.0.0.0",
	"parameters": {
		"factoryName": {
			"type": "string",
			"metadata": "Data Factory name",
			"defaultValue": "LEAP-DF-DataLoad"
		}
	},
	"variables": {
		"factoryId": "[concat('Microsoft.DataFactory/factories/', parameters('factoryName'))]"
	},
	"resources": [
		{
			"name": "[concat(parameters('factoryName'), '/pipeline5')]",
			"type": "Microsoft.DataFactory/factories/pipelines",
			"apiVersion": "2018-06-01",
			"properties": {
				"activities": [
					{
						"name": "FiveStar Data Transfer",
						"type": "Copy",
						"dependsOn": [],
						"policy": {
							"timeout": "7.00:00:00",
							"retry": 0,
							"retryIntervalInSeconds": 30,
							"secureOutput": false,
							"secureInput": false
						},
						"userProperties": [],
						"typeProperties": {
							"source": {
								"type": "AzureSqlSource",
								"queryTimeout": "02:00:00",
								"partitionOption": "None"
							},
							"sink": {
								"type": "SqlDWSink",
								"allowCopyCommand": true,
								"copyCommandSettings": {}
							},
							"enableStaging": true,
							"stagingSettings": {
								"linkedServiceName": {
									"referenceName": "DFPolybaseStagingStorageLink",
									"type": "LinkedServiceReference"
								},
								"path": "polybasestaging"
							},
							"translator": {
								"type": "TabularTranslator",
								"mappings": [
									{
										"source": {
											"name": "TeleCallingId",
											"type": "Int32"
										},
										"sink": {
											"name": "TelecallingID",
											"type": "Int32"
										}
									},
									{
										"source": {
											"name": "GPPoints",
											"type": "Byte"
										},
										"sink": {
											"name": "GPPOints",
											"type": "Byte"
										}
									},
									{
										"source": {
											"name": "ParameterId",
											"type": "Byte"
										},
										"sink": {
											"name": "Parameterid",
											"type": "Byte"
										}
									}
								]
							}
						},
						"inputs": [
							{
								"referenceName": "DS_TAS_tmpTeleCallingFiveStarGPPoints",
								"type": "DatasetReference",
								"parameters": {}
							}
						],
						"outputs": [
							{
								"referenceName": "DS_tmpTAS_FiveStarGPPoints",
								"type": "DatasetReference",
								"parameters": {}
							}
						]
					}
				],
				"policy": {
					"elapsedTimeMetric": {}
				},
				"folder": {
					"name": "V2 Pipelines"
				},
				"annotations": []
			},
			"dependsOn": []
		},
		{
			"name": "[concat(parameters('factoryName'), '/pipeline5_11Jun2022')]",
			"type": "Microsoft.DataFactory/factories/pipelines",
			"apiVersion": "2018-06-01",
			"properties": {
				"activities": [
					{
						"name": "spMoveOrderTeleCallingDataInHistory",
						"type": "SqlServerStoredProcedure",
						"dependsOn": [
							{
								"activity": "Copy tblTAS_tmpRAWTeleCallerListForDay",
								"dependencyConditions": [
									"Succeeded"
								]
							}
						],
						"policy": {
							"timeout": "7.00:00:00",
							"retry": 0,
							"retryIntervalInSeconds": 30,
							"secureOutput": false,
							"secureInput": false
						},
						"userProperties": [],
						"typeProperties": {
							"storedProcedureName": "[[dbo].[spMoveOrderTeleCallingDataInHistory]"
						},
						"linkedServiceName": {
							"referenceName": "TASDatabase_Check",
							"type": "LinkedServiceReference"
						}
					},
					{
						"name": "Copy tblTAS_tmpRAWTeleCallerListForDay",
						"type": "Copy",
						"dependsOn": [
							{
								"activity": "spTransferDFTeleCallerListForDayData",
								"dependencyConditions": [
									"Succeeded"
								]
							}
						],
						"policy": {
							"timeout": "7.00:00:00",
							"retry": 0,
							"retryIntervalInSeconds": 30,
							"secureOutput": false,
							"secureInput": false
						},
						"userProperties": [],
						"typeProperties": {
							"source": {
								"type": "AzureSqlSource",
								"queryTimeout": "02:00:00",
								"partitionOption": "None"
							},
							"sink": {
								"type": "SqlDWSink",
								"allowCopyCommand": true,
								"copyCommandSettings": {}
							},
							"enableStaging": true,
							"stagingSettings": {
								"linkedServiceName": {
									"referenceName": "DFPolybaseStagingStorageLink",
									"type": "LinkedServiceReference"
								},
								"path": "polybasestaging"
							},
							"translator": {
								"type": "TabularTranslator",
								"mappings": [
									{
										"source": {
											"name": "TeleCallingId",
											"type": "Int32"
										},
										"sink": {
											"name": "TeleCallingId",
											"type": "Int32"
										}
									},
									{
										"source": {
											"name": "AttendDetId",
											"type": "Int32"
										},
										"sink": {
											"name": "AttendDetId",
											"type": "Int32"
										}
									},
									{
										"source": {
											"name": "StoreId",
											"type": "Int32"
										},
										"sink": {
											"name": "StoreId",
											"type": "Int32"
										}
									},
									{
										"source": {
											"name": "Date",
											"type": "DateTime"
										},
										"sink": {
											"name": "Date",
											"type": "DateTime"
										}
									},
									{
										"source": {
											"name": "CallMade",
											"type": "DateTime"
										},
										"sink": {
											"name": "CallMade",
											"type": "DateTime"
										}
									},
									{
										"source": {
											"name": "DSENodeId",
											"type": "Int32"
										},
										"sink": {
											"name": "DSENodeId",
											"type": "Int32"
										}
									},
									{
										"source": {
											"name": "DSENodeType",
											"type": "Int32"
										},
										"sink": {
											"name": "DSENodeType",
											"type": "Int32"
										}
									},
									{
										"source": {
											"name": "BranchSubdNodeId",
											"type": "Int32"
										},
										"sink": {
											"name": "BranchSubdNodeId",
											"type": "Int32"
										}
									},
									{
										"source": {
											"name": "BranchSubdNodeType",
											"type": "Int32"
										},
										"sink": {
											"name": "BranchSubdNodeType",
											"type": "Int32"
										}
									},
									{
										"source": {
											"name": "StoreCode",
											"type": "String"
										},
										"sink": {
											"name": "StoreCode",
											"type": "String"
										}
									},
									{
										"source": {
											"name": "StoreName",
											"type": "String"
										},
										"sink": {
											"name": "StoreName",
											"type": "String"
										}
									},
									{
										"source": {
											"name": "ContactPerson",
											"type": "String"
										},
										"sink": {
											"name": "ContactPerson",
											"type": "String"
										}
									},
									{
										"source": {
											"name": "ContactNo",
											"type": "String"
										},
										"sink": {
											"name": "ContactNo",
											"type": "String"
										}
									},
									{
										"source": {
											"name": "Channel",
											"type": "String"
										},
										"sink": {
											"name": "Channel",
											"type": "String"
										}
									},
									{
										"source": {
											"name": "SectorId",
											"type": "Int32"
										},
										"sink": {
											"name": "SectorId",
											"type": "Int32"
										}
									},
									{
										"source": {
											"name": "flgCallStatus",
											"type": "Byte"
										},
										"sink": {
											"name": "flgCallStatus",
											"type": "Byte"
										}
									},
									{
										"source": {
											"name": "ScheduleCall",
											"type": "String"
										},
										"sink": {
											"name": "ScheduleCall",
											"type": "String"
										}
									},
									{
										"source": {
											"name": "ReasonId",
											"type": "Int32"
										},
										"sink": {
											"name": "ReasonId",
											"type": "Int32"
										}
									},
									{
										"source": {
											"name": "CallAttempt",
											"type": "Byte"
										},
										"sink": {
											"name": "CallAttempt",
											"type": "Byte"
										}
									},
									{
										"source": {
											"name": "TeleReasonId",
											"type": "Int32"
										},
										"sink": {
											"name": "TeleReasonId",
											"type": "Int32"
										}
									},
									{
										"source": {
											"name": "TeleUserId",
											"type": "Int32"
										},
										"sink": {
											"name": "TeleUserId",
											"type": "Int32"
										}
									},
									{
										"source": {
											"name": "Priority",
											"type": "Int16"
										},
										"sink": {
											"name": "Priority",
											"type": "Int16"
										}
									},
									{
										"source": {
											"name": "TotalSales",
											"type": "Decimal"
										},
										"sink": {
											"name": "TotalSales",
											"type": "Decimal"
										}
									},
									{
										"source": {
											"name": "NoOfInv",
											"type": "Int32"
										},
										"sink": {
											"name": "NoOfInv",
											"type": "Int32"
										}
									},
									{
										"source": {
											"name": "LastCallDate",
											"type": "DateTime"
										},
										"sink": {
											"name": "LastCallDate",
											"type": "DateTime"
										}
									},
									{
										"source": {
											"name": "IsFinalDownloadSubmit",
											"type": "Boolean"
										},
										"sink": {
											"name": "IsFinalDownloadSubmit",
											"type": "Boolean"
										}
									},
									{
										"source": {
											"name": "IsDownloaded",
											"type": "Boolean"
										},
										"sink": {
											"name": "IsDownloaded",
											"type": "Boolean"
										}
									},
									{
										"source": {
											"name": "OutStandingAmt",
											"type": "Decimal"
										},
										"sink": {
											"name": "OutStandingAmt",
											"type": "Decimal"
										}
									},
									{
										"source": {
											"name": "OutStandingDate",
											"type": "DateTime"
										},
										"sink": {
											"name": "OutStandingDate",
											"type": "DateTime"
										}
									},
									{
										"source": {
											"name": "InvNo",
											"type": "String"
										},
										"sink": {
											"name": "InvNo",
											"type": "String"
										}
									},
									{
										"source": {
											"name": "InvDate",
											"type": "DateTime"
										},
										"sink": {
											"name": "InvDate",
											"type": "DateTime"
										}
									},
									{
										"source": {
											"name": "LoginIdUpd",
											"type": "Int32"
										},
										"sink": {
											"name": "LoginIdUpd",
											"type": "Int32"
										}
									},
									{
										"source": {
											"name": "TimeSTampUpd",
											"type": "DateTime"
										},
										"sink": {
											"name": "TimeSTampUpd",
											"type": "DateTime"
										}
									},
									{
										"source": {
											"name": "OldTeleCallingId",
											"type": "Int32"
										},
										"sink": {
											"name": "OldTeleCallingId",
											"type": "Int32"
										}
									},
									{
										"source": {
											"name": "TimeStampIns",
											"type": "DateTime"
										},
										"sink": {
											"name": "TimeStampIns",
											"type": "DateTime"
										}
									},
									{
										"source": {
											"name": "TCRouteCalendarId",
											"type": "Int32"
										},
										"sink": {
											"name": "TCRouteCalendarId",
											"type": "Int32"
										}
									},
									{
										"source": {
											"name": "TCPlanCallsMapId",
											"type": "Int32"
										},
										"sink": {
											"name": "TCPlanCallsMapId",
											"type": "Int32"
										}
									},
									{
										"source": {
											"name": "LoginIdIns",
											"type": "Int32"
										},
										"sink": {
											"name": "LoginIdIns",
											"type": "Int32"
										}
									},
									{
										"source": {
											"name": "ChannelId",
											"type": "Int32"
										},
										"sink": {
											"name": "ChannelId",
											"type": "Int32"
										}
									},
									{
										"source": {
											"name": "RuleId",
											"type": "Int32"
										},
										"sink": {
											"name": "RuleId",
											"type": "Int32"
										}
									},
									{
										"source": {
											"name": "ScheduleDate",
											"type": "DateTime"
										},
										"sink": {
											"name": "ScheduleDate",
											"type": "DateTime"
										}
									},
									{
										"source": {
											"name": "CallStartDate",
											"type": "DateTime"
										},
										"sink": {
											"name": "CallStartDate",
											"type": "DateTime"
										}
									},
									{
										"source": {
											"name": "Remarks",
											"type": "String"
										},
										"sink": {
											"name": "Remarks",
											"type": "String"
										}
									},
									{
										"source": {
											"name": "LastOrderDate",
											"type": "DateTime"
										},
										"sink": {
											"name": "LastOrderDate",
											"type": "DateTime"
										}
									},
									{
										"source": {
											"name": "LastOrderValue",
											"type": "Decimal"
										},
										"sink": {
											"name": "LastOrderValue",
											"type": "Decimal"
										}
									},
									{
										"source": {
											"name": "OrderBy",
											"type": "String"
										},
										"sink": {
											"name": "OrderBy",
											"type": "String"
										}
									},
									{
										"source": {
											"name": "LastVisit",
											"type": "DateTime"
										},
										"sink": {
											"name": "LastVisit",
											"type": "DateTime"
										}
									},
									{
										"source": {
											"name": "LastVisitStatus",
											"type": "String"
										},
										"sink": {
											"name": "LastVisitStatus",
											"type": "String"
										}
									},
									{
										"source": {
											"name": "VisitedBy",
											"type": "String"
										},
										"sink": {
											"name": "VisitedBy",
											"type": "String"
										}
									},
									{
										"source": {
											"name": "LastCall",
											"type": "DateTime"
										},
										"sink": {
											"name": "LastCall",
											"type": "DateTime"
										}
									},
									{
										"source": {
											"name": "LastCallStatus",
											"type": "String"
										},
										"sink": {
											"name": "LastCallStatus",
											"type": "String"
										}
									},
									{
										"source": {
											"name": "LastCalledBY",
											"type": "String"
										},
										"sink": {
											"name": "LastCalledBY",
											"type": "String"
										}
									},
									{
										"source": {
											"name": "SubChannelId",
											"type": "Int32"
										},
										"sink": {
											"name": "SubChannelId",
											"type": "Int32"
										}
									},
									{
										"source": {
											"name": "SubChannel",
											"type": "String"
										},
										"sink": {
											"name": "SubChannel",
											"type": "String"
										}
									},
									{
										"source": {
											"name": "FrequencyId",
											"type": "Byte"
										},
										"sink": {
											"name": "FrequencyId",
											"type": "Byte"
										}
									},
									{
										"source": {
											"name": "AlternateContactNo",
											"type": "String"
										},
										"sink": {
											"name": "AlternateContactNo",
											"type": "String"
										}
									},
									{
										"source": {
											"name": "RouteName",
											"type": "String"
										},
										"sink": {
											"name": "RouteName",
											"type": "String"
										}
									},
									{
										"source": {
											"name": "FiveStarRuleId",
											"type": "Byte"
										},
										"sink": {
											"name": "FiveStarRuleId",
											"type": "Byte"
										}
									},
									{
										"source": {
											"name": "FiveStarNoOfGPTgt",
											"type": "Byte"
										},
										"sink": {
											"name": "FiveStarNoOfGPTgt",
											"type": "Byte"
										}
									},
									{
										"source": {
											"name": "FiveStarNoOfLSSTgt",
											"type": "Byte"
										},
										"sink": {
											"name": "FiveStarNoOfLSSTgt",
											"type": "Byte"
										}
									},
									{
										"source": {
											"name": "FiveStarIndTgtDlvryVal",
											"type": "Decimal"
										},
										"sink": {
											"name": "FiveStarIndTgtDlvryVal",
											"type": "Decimal"
										}
									},
									{
										"source": {
											"name": "FiveStarProductivityTgt",
											"type": "Decimal"
										},
										"sink": {
											"name": "FiveStarProductivityTgt",
											"type": "Decimal"
										}
									},
									{
										"source": {
											"name": "TotOrderVal",
											"type": "Decimal"
										},
										"sink": {
											"name": "TotOrderVal",
											"type": "Decimal"
										}
									},
									{
										"source": {
											"name": "NoOfSKU",
											"type": "Int32"
										},
										"sink": {
											"name": "NoOfSKU",
											"type": "Int32"
										}
									},
									{
										"source": {
											"name": "FiveStarNoOfGPAct",
											"type": "Byte"
										},
										"sink": {
											"name": "FiveStarNoOfGPAct",
											"type": "Byte"
										}
									},
									{
										"source": {
											"name": "FiveStarNoOfLSSAct",
											"type": "Byte"
										},
										"sink": {
											"name": "FiveStarNoOfLSSAct",
											"type": "Byte"
										}
									},
									{
										"source": {
											"name": "FiveStarTotIndTgtDlvryVal",
											"type": "Decimal"
										},
										"sink": {
											"name": "FiveStarTotIndTgtDlvryVal",
											"type": "Decimal"
										}
									},
									{
										"source": {
											"name": "FiveStarAlrdyAchIndTgtDlvryVal",
											"type": "Decimal"
										},
										"sink": {
											"name": "FiveStarAlrdyAchIndTgtDlvryVal",
											"type": "Decimal"
										}
									},
									{
										"source": {
											"name": "NoOfStarsAch",
											"type": "Byte"
										},
										"sink": {
											"name": "NoOfStarsAch",
											"type": "Byte"
										}
									},
									{
										"source": {
											"name": "NoOfPendingVisits",
											"type": "Byte"
										},
										"sink": {
											"name": "NoOfPendingVisits",
											"type": "Byte"
										}
									},
									{
										"source": {
											"name": "TotInvVal",
											"type": "Decimal"
										},
										"sink": {
											"name": "TotInvVal",
											"type": "Decimal"
										}
									},
									{
										"source": {
											"name": "FiveStarNoOfGPAchieved",
											"type": "Byte"
										},
										"sink": {
											"name": "FiveStarNoOfGPAchieved",
											"type": "Byte"
										}
									},
									{
										"source": {
											"name": "FiveStarNoOfLSSAchieved",
											"type": "Byte"
										},
										"sink": {
											"name": "FiveStarNoOfLSSAchieved",
											"type": "Byte"
										}
									},
									{
										"source": {
											"name": "DSEIssueIds",
											"type": "String"
										},
										"sink": {
											"name": "DSEIssueIds",
											"type": "String"
										}
									},
									{
										"source": {
											"name": "DSEComments",
											"type": "String"
										},
										"sink": {
											"name": "DSEComments",
											"type": "String"
										}
									},
									{
										"source": {
											"name": "flgCCRRoleOver",
											"type": "Byte"
										},
										"sink": {
											"name": "flgCCRRoleOver",
											"type": "Byte"
										}
									},
									{
										"source": {
											"name": "TCNodeId",
											"type": "Int32"
										},
										"sink": {
											"name": "TCNodeId",
											"type": "Int32"
										}
									},
									{
										"source": {
											"name": "TCNodeType",
											"type": "Int32"
										},
										"sink": {
											"name": "TCNodeType",
											"type": "Int32"
										}
									},
									{
										"source": {
											"name": "OrderCode",
											"type": "String"
										},
										"sink": {
											"name": "OrderCode",
											"type": "String"
										}
									}
								]
							}
						},
						"inputs": [
							{
								"referenceName": "DS_TAS_tblTAS_tmpRAWTeleCallerListForDay_V2",
								"type": "DatasetReference",
								"parameters": {}
							}
						],
						"outputs": [
							{
								"referenceName": "DS_tblTAS_TeleCallerListForDay",
								"type": "DatasetReference",
								"parameters": {}
							}
						]
					},
					{
						"name": "spTransferDFTeleCallerListForDayData",
						"type": "SqlServerStoredProcedure",
						"dependsOn": [],
						"policy": {
							"timeout": "7.00:00:00",
							"retry": 0,
							"retryIntervalInSeconds": 30,
							"secureOutput": false,
							"secureInput": false
						},
						"userProperties": [],
						"typeProperties": {
							"storedProcedureName": "[[dbo].[spTransferDFTeleCallerListForDayData]"
						},
						"linkedServiceName": {
							"referenceName": "TASDatabase_Check",
							"type": "LinkedServiceReference"
						}
					}
				],
				"policy": {
					"elapsedTimeMetric": {}
				},
				"folder": {
					"name": "V2 Pipelines"
				},
				"annotations": []
			},
			"dependsOn": []
		},
		{
			"name": "[concat(parameters('factoryName'), '/pipeline6')]",
			"type": "Microsoft.DataFactory/factories/pipelines",
			"apiVersion": "2018-06-01",
			"properties": {
				"activities": [
					{
						"name": "spTAS_PopulateStoreSchemeDistributionCount-TAS",
						"type": "SqlServerStoredProcedure",
						"state": "Inactive",
						"onInactiveMarkAs": "Succeeded",
						"dependsOn": [
							{
								"activity": "spTAS_PopulateStoreSchemeDistributionCount-TAS-New",
								"dependencyConditions": [
									"Succeeded"
								]
							}
						],
						"policy": {
							"timeout": "7.00:00:00",
							"retry": 0,
							"retryIntervalInSeconds": 30,
							"secureOutput": false,
							"secureInput": false
						},
						"userProperties": [],
						"typeProperties": {
							"storedProcedureName": "[[dbo].[spTAS_PopulateStoreSchemeDistributionCount]"
						},
						"linkedServiceName": {
							"referenceName": "TASDatabase_Check",
							"type": "LinkedServiceReference"
						}
					},
					{
						"name": "spTAS_PopulateStoreSchemeDistributionCount-TAS-New",
						"type": "SqlServerStoredProcedure",
						"dependsOn": [
							{
								"activity": "Lookup1",
								"dependencyConditions": [
									"Succeeded"
								]
							}
						],
						"policy": {
							"timeout": "0.12:00:00",
							"retry": 0,
							"retryIntervalInSeconds": 30,
							"secureOutput": false,
							"secureInput": false
						},
						"userProperties": [],
						"typeProperties": {
							"storedProcedureName": "[[dbo].[spTAS_PopulateStoreSchemeDistributionCount]"
						},
						"linkedServiceName": {
							"referenceName": "TASDatabase_Check",
							"type": "LinkedServiceReference"
						}
					},
					{
						"name": "Lookup1",
						"type": "Lookup",
						"state": "Inactive",
						"onInactiveMarkAs": "Succeeded",
						"dependsOn": [
							{
								"activity": "Stored procedure1",
								"dependencyConditions": [
									"Succeeded"
								]
							}
						],
						"policy": {
							"timeout": "0.12:00:00",
							"retry": 0,
							"retryIntervalInSeconds": 30,
							"secureOutput": false,
							"secureInput": false
						},
						"userProperties": [],
						"typeProperties": {
							"source": {
								"type": "AzureSqlSource",
								"sqlReaderQuery": "SELECT TOp 10 * FROM epathshalanewloginsheet",
								"queryTimeout": "02:00:00",
								"partitionOption": "None"
							},
							"dataset": {
								"referenceName": "DS_TASDestination_table",
								"type": "DatasetReference",
								"parameters": {
									"tablename": "epathshalanewloginsheet"
								}
							}
						}
					},
					{
						"name": "Stored procedure1",
						"type": "SqlServerStoredProcedure",
						"state": "Inactive",
						"onInactiveMarkAs": "Succeeded",
						"dependsOn": [],
						"policy": {
							"timeout": "0.12:00:00",
							"retry": 0,
							"retryIntervalInSeconds": 30,
							"secureOutput": false,
							"secureInput": false
						},
						"userProperties": [],
						"typeProperties": {
							"storedProcedureName": "[[dbo].[spCountTables]"
						},
						"linkedServiceName": {
							"referenceName": "TASDatabase_V2",
							"type": "LinkedServiceReference"
						}
					}
				],
				"policy": {
					"elapsedTimeMetric": {}
				},
				"folder": {
					"name": "V2 Pipelines"
				},
				"annotations": []
			},
			"dependsOn": []
		},
		{
			"name": "[concat(parameters('factoryName'), '/scalecheck')]",
			"type": "Microsoft.DataFactory/factories/pipelines",
			"apiVersion": "2018-06-01",
			"properties": {
				"activities": [
					{
						"name": "DW_Resume_Scale_V2",
						"type": "ExecutePipeline",
						"dependsOn": [],
						"policy": {
							"secureInput": false
						},
						"userProperties": [],
						"typeProperties": {
							"pipeline": {
								"referenceName": "DW_Resume_Scale_V2",
								"type": "PipelineReference"
							},
							"waitOnCompletion": true,
							"parameters": {
								"ScaleVal": "DW200c",
								"flgcalled": 1
							}
						}
					}
				],
				"policy": {
					"elapsedTimeMetric": {}
				},
				"annotations": []
			},
			"dependsOn": []
		},
		{
			"name": "[concat(parameters('factoryName'), '/tblTAS_SBStoreWiseBaseDetailsActual_01Mar2023')]",
			"type": "Microsoft.DataFactory/factories/pipelines",
			"apiVersion": "2018-06-01",
			"properties": {
				"activities": [
					{
						"name": "Copy tblTAS_SBStoreWiseBaseDetailsActual",
						"type": "Copy",
						"dependsOn": [],
						"policy": {
							"timeout": "7.00:00:00",
							"retry": 0,
							"retryIntervalInSeconds": 30,
							"secureOutput": false,
							"secureInput": false
						},
						"userProperties": [],
						"typeProperties": {
							"source": {
								"type": "SqlDWSource",
								"queryTimeout": "02:00:00",
								"partitionOption": "None"
							},
							"sink": {
								"type": "AzureSqlSink",
								"writeBehavior": "insert",
								"sqlWriterUseTableLock": false,
								"disableMetricsCollection": false
							},
							"enableStaging": false,
							"translator": {
								"type": "TabularTranslator",
								"mappings": [
									{
										"source": {
											"name": "StoreId",
											"type": "Int32",
											"physicalType": "int"
										},
										"sink": {
											"name": "StoreId",
											"type": "Int32",
											"physicalType": "int"
										}
									},
									{
										"source": {
											"name": "SBFNodeId",
											"type": "Int32",
											"physicalType": "int"
										},
										"sink": {
											"name": "SBFNodeId",
											"type": "Int32",
											"physicalType": "int"
										}
									},
									{
										"source": {
											"name": "NoOfTimesSold",
											"type": "Int32",
											"physicalType": "int"
										},
										"sink": {
											"name": "NoOfTimesSold",
											"type": "Int32",
											"physicalType": "int"
										}
									},
									{
										"source": {
											"name": "SalesValue",
											"type": "Decimal",
											"physicalType": "decimal",
											"scale": 0,
											"precision": 18
										},
										"sink": {
											"name": "SalesValue",
											"type": "Decimal",
											"physicalType": "decimal",
											"scale": 0,
											"precision": 18
										}
									},
									{
										"source": {
											"name": "RetValue",
											"type": "Decimal",
											"physicalType": "decimal",
											"scale": 0,
											"precision": 18
										},
										"sink": {
											"name": "RetValue",
											"type": "Decimal",
											"physicalType": "decimal",
											"scale": 0,
											"precision": 18
										}
									},
									{
										"source": {
											"name": "NetSalesValue",
											"type": "Decimal",
											"physicalType": "decimal",
											"scale": 0,
											"precision": 18
										},
										"sink": {
											"name": "NetSalesValue",
											"type": "Decimal",
											"physicalType": "decimal",
											"scale": 0,
											"precision": 18
										}
									},
									{
										"source": {
											"name": "LastInvDate",
											"type": "DateTime",
											"physicalType": "date"
										},
										"sink": {
											"name": "LastInvDate",
											"type": "DateTime",
											"physicalType": "date"
										}
									}
								],
								"typeConversion": true,
								"typeConversionSettings": {
									"allowDataTruncation": true,
									"treatBooleanAsNumber": false
								}
							}
						},
						"inputs": [
							{
								"referenceName": "DS_DW_tblTAS_SBStoreWiseBaseDetailsActual",
								"type": "DatasetReference",
								"parameters": {}
							}
						],
						"outputs": [
							{
								"referenceName": "DS_TAS_tblSBStoreWiseBaseDetailsActual_test",
								"type": "DatasetReference",
								"parameters": {}
							}
						]
					}
				],
				"policy": {
					"elapsedTimeMetric": {}
				},
				"annotations": []
			},
			"dependsOn": []
		},
		{
			"name": "[concat(parameters('factoryName'), '/ADLSBinaryDataSource_Container')]",
			"type": "Microsoft.DataFactory/factories/datasets",
			"apiVersion": "2018-06-01",
			"properties": {
				"description": "It describes the folder in the data source store.",
				"linkedServiceName": {
					"referenceName": "LinkedService_PnGADLS",
					"type": "LinkedServiceReference"
				},
				"parameters": {
					"Container": {
						"type": "String"
					}
				},
				"folder": {
					"name": "OtherDataSet"
				},
				"annotations": [],
				"type": "Binary",
				"typeProperties": {
					"location": {
						"type": "AzureBlobFSLocation",
						"fileSystem": {
							"value": "@{dataset().Container}",
							"type": "Expression"
						}
					}
				}
			},
			"dependsOn": []
		},
		{
			"name": "[concat(parameters('factoryName'), '/ADLSBinaryDataSource_File')]",
			"type": "Microsoft.DataFactory/factories/datasets",
			"apiVersion": "2018-06-01",
			"properties": {
				"description": "It describes the file in the data source store.",
				"linkedServiceName": {
					"referenceName": "LinkedService_PnGADLS",
					"type": "LinkedServiceReference"
				},
				"parameters": {
					"Container": {
						"type": "String"
					},
					"Directory": {
						"type": "String"
					},
					"filename": {
						"type": "string"
					}
				},
				"folder": {
					"name": "OtherDataSet"
				},
				"annotations": [],
				"type": "Binary",
				"typeProperties": {
					"location": {
						"type": "AzureBlobFSLocation",
						"fileName": {
							"value": "@dataset().filename",
							"type": "Expression"
						},
						"folderPath": {
							"value": "@{dataset().Directory}",
							"type": "Expression"
						},
						"fileSystem": {
							"value": "@{dataset().Container}",
							"type": "Expression"
						}
					}
				}
			},
			"dependsOn": []
		},
		{
			"name": "[concat(parameters('factoryName'), '/ADLSBinaryDataSource_Folder')]",
			"type": "Microsoft.DataFactory/factories/datasets",
			"apiVersion": "2018-06-01",
			"properties": {
				"description": "It describes the folder in the data source store.",
				"linkedServiceName": {
					"referenceName": "LinkedService_PnGADLS",
					"type": "LinkedServiceReference"
				},
				"parameters": {
					"Container": {
						"type": "String"
					},
					"Directory": {
						"type": "String"
					}
				},
				"folder": {
					"name": "OtherDataSet"
				},
				"annotations": [],
				"type": "Binary",
				"typeProperties": {
					"location": {
						"type": "AzureBlobFSLocation",
						"folderPath": {
							"value": "@{dataset().Directory}",
							"type": "Expression"
						},
						"fileSystem": {
							"value": "@{dataset().Container}",
							"type": "Expression"
						}
					}
				}
			},
			"dependsOn": []
		},
		{
			"name": "[concat(parameters('factoryName'), '/ADLSCSVDataSource_File')]",
			"type": "Microsoft.DataFactory/factories/datasets",
			"apiVersion": "2018-06-01",
			"properties": {
				"linkedServiceName": {
					"referenceName": "LinkedService_PnGADLS",
					"type": "LinkedServiceReference"
				},
				"parameters": {
					"Container": {
						"type": "string"
					},
					"Directory": {
						"type": "string"
					},
					"Filename": {
						"type": "string"
					}
				},
				"folder": {
					"name": "OtherDataSet"
				},
				"annotations": [],
				"type": "DelimitedText",
				"typeProperties": {
					"location": {
						"type": "AzureBlobFSLocation",
						"fileName": {
							"value": "@dataset().Filename",
							"type": "Expression"
						},
						"folderPath": {
							"value": "@dataset().Directory",
							"type": "Expression"
						},
						"fileSystem": {
							"value": "@dataset().Container",
							"type": "Expression"
						}
					},
					"columnDelimiter": "|",
					"compressionCodec": "gzip",
					"compressionLevel": "Optimal",
					"escapeChar": "\\",
					"firstRowAsHeader": true,
					"quoteChar": "\""
				},
				"schema": [
					{
						"name": "document_no",
						"type": "String"
					},
					{
						"name": "apply_to_doc",
						"type": "String"
					},
					{
						"name": "document_date",
						"type": "String"
					},
					{
						"name": "transaction_type",
						"type": "String"
					},
					{
						"name": "subbrandform_name",
						"type": "String"
					},
					{
						"name": "prod_name",
						"type": "String"
					},
					{
						"name": "customer_name",
						"type": "String"
					},
					{
						"name": "customer_code",
						"type": "String"
					},
					{
						"name": "channel_description",
						"type": "String"
					},
					{
						"name": "dse",
						"type": "String"
					},
					{
						"name": "pcode",
						"type": "String"
					},
					{
						"name": "customer_type",
						"type": "String"
					},
					{
						"name": "hsn_code",
						"type": "String"
					},
					{
						"name": "category",
						"type": "String"
					},
					{
						"name": "brand",
						"type": "String"
					},
					{
						"name": "brandform",
						"type": "String"
					},
					{
						"name": "quantity",
						"type": "String"
					},
					{
						"name": "gross_value",
						"type": "String"
					},
					{
						"name": "discount",
						"type": "String"
					},
					{
						"name": "taxable_scheme",
						"type": "String"
					},
					{
						"name": "cgsttax",
						"type": "String"
					},
					{
						"name": "sgsttax",
						"type": "String"
					},
					{
						"name": "igsttax",
						"type": "String"
					},
					{
						"name": "cesstax",
						"type": "String"
					},
					{
						"name": "mracc_code",
						"type": "String"
					},
					{
						"name": "mracc_desc",
						"type": "String"
					},
					{
						"name": "vendor",
						"type": "String"
					},
					{
						"name": "net_amount",
						"type": "String"
					},
					{
						"name": "tax_on_discount",
						"type": "String"
					},
					{
						"name": "tax_on_scheme",
						"type": "String"
					},
					{
						"name": "tax_in_rlp",
						"type": "String"
					},
					{
						"name": "retailing",
						"type": "String"
					},
					{
						"name": "gross_in_slp",
						"type": "String"
					},
					{
						"name": "po_no",
						"type": "String"
					},
					{
						"name": "dse_code",
						"type": "String"
					},
					{
						"name": "msu",
						"type": "String"
					},
					{
						"name": "reason",
						"type": "String"
					},
					{
						"name": "dist_gstinno",
						"type": "String"
					},
					{
						"name": "ret_gstinno",
						"type": "String"
					},
					{
						"name": "srn_ref_no",
						"type": "String"
					},
					{
						"name": "composite",
						"type": "String"
					},
					{
						"name": "cgsttax_rate",
						"type": "String"
					},
					{
						"name": "sgsttax_rate",
						"type": "String"
					},
					{
						"name": "igsttax_rate",
						"type": "String"
					},
					{
						"name": "cesstax_rate",
						"type": "String"
					},
					{
						"name": "branch_code",
						"type": "String"
					},
					{
						"name": "branch_name",
						"type": "String"
					},
					{
						"name": "order_mode",
						"type": "String"
					},
					{
						"name": "tc_code",
						"type": "String"
					},
					{
						"name": "tc_name",
						"type": "String"
					}
				]
			},
			"dependsOn": []
		},
		{
			"name": "[concat(parameters('factoryName'), '/ADLSCSVDataSource_File_withoutGzip')]",
			"type": "Microsoft.DataFactory/factories/datasets",
			"apiVersion": "2018-06-01",
			"properties": {
				"linkedServiceName": {
					"referenceName": "LinkedService_PnGADLS",
					"type": "LinkedServiceReference"
				},
				"parameters": {
					"Container": {
						"type": "string"
					},
					"Directory": {
						"type": "string"
					},
					"Filename": {
						"type": "string"
					}
				},
				"folder": {
					"name": "OtherDataSet"
				},
				"annotations": [],
				"type": "DelimitedText",
				"typeProperties": {
					"location": {
						"type": "AzureBlobFSLocation",
						"fileName": {
							"value": "@dataset().Filename",
							"type": "Expression"
						},
						"folderPath": {
							"value": "@dataset().Directory",
							"type": "Expression"
						},
						"fileSystem": {
							"value": "@dataset().Container",
							"type": "Expression"
						}
					},
					"columnDelimiter": ",",
					"escapeChar": "\\",
					"firstRowAsHeader": false,
					"quoteChar": "\""
				},
				"schema": [
					{
						"name": "document_no",
						"type": "String"
					},
					{
						"name": "apply_to_doc",
						"type": "String"
					},
					{
						"name": "document_date",
						"type": "String"
					},
					{
						"name": "transaction_type",
						"type": "String"
					},
					{
						"name": "subbrandform_name",
						"type": "String"
					},
					{
						"name": "prod_name",
						"type": "String"
					},
					{
						"name": "customer_name",
						"type": "String"
					},
					{
						"name": "customer_code",
						"type": "String"
					},
					{
						"name": "channel_description",
						"type": "String"
					},
					{
						"name": "dse",
						"type": "String"
					},
					{
						"name": "pcode",
						"type": "String"
					},
					{
						"name": "customer_type",
						"type": "String"
					},
					{
						"name": "hsn_code",
						"type": "String"
					},
					{
						"name": "category",
						"type": "String"
					},
					{
						"name": "brand",
						"type": "String"
					},
					{
						"name": "brandform",
						"type": "String"
					},
					{
						"name": "quantity",
						"type": "String"
					},
					{
						"name": "gross_value",
						"type": "String"
					},
					{
						"name": "discount",
						"type": "String"
					},
					{
						"name": "taxable_scheme",
						"type": "String"
					},
					{
						"name": "cgsttax",
						"type": "String"
					},
					{
						"name": "sgsttax",
						"type": "String"
					},
					{
						"name": "igsttax",
						"type": "String"
					},
					{
						"name": "cesstax",
						"type": "String"
					},
					{
						"name": "mracc_code",
						"type": "String"
					},
					{
						"name": "mracc_desc",
						"type": "String"
					},
					{
						"name": "vendor",
						"type": "String"
					},
					{
						"name": "net_amount",
						"type": "String"
					},
					{
						"name": "tax_on_discount",
						"type": "String"
					},
					{
						"name": "tax_on_scheme",
						"type": "String"
					},
					{
						"name": "tax_in_rlp",
						"type": "String"
					},
					{
						"name": "retailing",
						"type": "String"
					},
					{
						"name": "gross_in_slp",
						"type": "String"
					},
					{
						"name": "po_no",
						"type": "String"
					},
					{
						"name": "dse_code",
						"type": "String"
					},
					{
						"name": "msu",
						"type": "String"
					},
					{
						"name": "reason",
						"type": "String"
					},
					{
						"name": "dist_gstinno",
						"type": "String"
					},
					{
						"name": "ret_gstinno",
						"type": "String"
					},
					{
						"name": "srn_ref_no",
						"type": "String"
					},
					{
						"name": "composite",
						"type": "String"
					},
					{
						"name": "cgsttax_rate",
						"type": "String"
					},
					{
						"name": "sgsttax_rate",
						"type": "String"
					},
					{
						"name": "igsttax_rate",
						"type": "String"
					},
					{
						"name": "cesstax_rate",
						"type": "String"
					},
					{
						"name": "branch_code",
						"type": "String"
					},
					{
						"name": "branch_name",
						"type": "String"
					},
					{
						"name": "order_mode",
						"type": "String"
					},
					{
						"name": "tc_code",
						"type": "String"
					},
					{
						"name": "tc_name",
						"type": "String"
					}
				]
			},
			"dependsOn": []
		},
		{
			"name": "[concat(parameters('factoryName'), '/ADLSCSVDataSource_Folder')]",
			"type": "Microsoft.DataFactory/factories/datasets",
			"apiVersion": "2018-06-01",
			"properties": {
				"linkedServiceName": {
					"referenceName": "dfdatafoundationLink",
					"type": "LinkedServiceReference"
				},
				"parameters": {
					"Container": {
						"type": "string"
					},
					"Directory": {
						"type": "string"
					}
				},
				"folder": {
					"name": "OtherDataSet"
				},
				"annotations": [],
				"type": "DelimitedText",
				"typeProperties": {
					"location": {
						"type": "AzureBlobStorageLocation",
						"fileName": "DPSR_cloud01_2020Oct06.gz",
						"folderPath": {
							"value": "@dataset().Directory",
							"type": "Expression"
						},
						"container": {
							"value": "@dataset().Container",
							"type": "Expression"
						}
					},
					"columnDelimiter": "|",
					"compressionCodec": "gzip",
					"compressionLevel": "Optimal",
					"escapeChar": "\\",
					"firstRowAsHeader": true,
					"quoteChar": "\""
				},
				"schema": [
					{
						"name": "document_no",
						"type": "String"
					},
					{
						"name": "apply_to_doc",
						"type": "String"
					},
					{
						"name": "document_date",
						"type": "String"
					},
					{
						"name": "transaction_type",
						"type": "String"
					},
					{
						"name": "subbrandform_name",
						"type": "String"
					},
					{
						"name": "prod_name",
						"type": "String"
					},
					{
						"name": "customer_name",
						"type": "String"
					},
					{
						"name": "customer_code",
						"type": "String"
					},
					{
						"name": "channel_description",
						"type": "String"
					},
					{
						"name": "dse",
						"type": "String"
					},
					{
						"name": "pcode",
						"type": "String"
					},
					{
						"name": "customer_type",
						"type": "String"
					},
					{
						"name": "hsn_code",
						"type": "String"
					},
					{
						"name": "category",
						"type": "String"
					},
					{
						"name": "brand",
						"type": "String"
					},
					{
						"name": "brandform",
						"type": "String"
					},
					{
						"name": "quantity",
						"type": "String"
					},
					{
						"name": "gross_value",
						"type": "String"
					},
					{
						"name": "discount",
						"type": "String"
					},
					{
						"name": "taxable_scheme",
						"type": "String"
					},
					{
						"name": "cgsttax",
						"type": "String"
					},
					{
						"name": "sgsttax",
						"type": "String"
					},
					{
						"name": "igsttax",
						"type": "String"
					},
					{
						"name": "cesstax",
						"type": "String"
					},
					{
						"name": "mracc_code",
						"type": "String"
					},
					{
						"name": "mracc_desc",
						"type": "String"
					},
					{
						"name": "vendor",
						"type": "String"
					},
					{
						"name": "net_amount",
						"type": "String"
					},
					{
						"name": "tax_on_discount",
						"type": "String"
					},
					{
						"name": "tax_on_scheme",
						"type": "String"
					},
					{
						"name": "tax_in_rlp",
						"type": "String"
					},
					{
						"name": "retailing",
						"type": "String"
					},
					{
						"name": "gross_in_slp",
						"type": "String"
					},
					{
						"name": "po_no",
						"type": "String"
					},
					{
						"name": "dse_code",
						"type": "String"
					},
					{
						"name": "msu",
						"type": "String"
					},
					{
						"name": "reason",
						"type": "String"
					},
					{
						"name": "dist_gstinno",
						"type": "String"
					},
					{
						"name": "ret_gstinno",
						"type": "String"
					},
					{
						"name": "srn_ref_no",
						"type": "String"
					},
					{
						"name": "composite",
						"type": "String"
					},
					{
						"name": "cgsttax_rate",
						"type": "String"
					},
					{
						"name": "sgsttax_rate",
						"type": "String"
					},
					{
						"name": "igsttax_rate",
						"type": "String"
					},
					{
						"name": "cesstax_rate",
						"type": "String"
					},
					{
						"name": "branch_code",
						"type": "String"
					},
					{
						"name": "branch_name",
						"type": "String"
					},
					{
						"name": "order_mode",
						"type": "String"
					},
					{
						"name": "tc_code",
						"type": "String"
					},
					{
						"name": "tc_name",
						"type": "String"
					}
				]
			},
			"dependsOn": []
		},
		{
			"name": "[concat(parameters('factoryName'), '/ADLSCSVDataSource_Folder_WithComma')]",
			"type": "Microsoft.DataFactory/factories/datasets",
			"apiVersion": "2018-06-01",
			"properties": {
				"linkedServiceName": {
					"referenceName": "dfdatafoundationLink",
					"type": "LinkedServiceReference"
				},
				"parameters": {
					"Container": {
						"type": "string"
					},
					"Directory": {
						"type": "string"
					}
				},
				"folder": {
					"name": "OtherDataSet"
				},
				"annotations": [],
				"type": "DelimitedText",
				"typeProperties": {
					"location": {
						"type": "AzureBlobStorageLocation",
						"fileName": "Cochin29022020.gz",
						"folderPath": {
							"value": "@dataset().Directory",
							"type": "Expression"
						},
						"container": {
							"value": "@dataset().Container",
							"type": "Expression"
						}
					},
					"columnDelimiter": ",",
					"compressionCodec": "gzip",
					"compressionLevel": "Optimal",
					"escapeChar": "\\",
					"firstRowAsHeader": true,
					"quoteChar": "\""
				},
				"schema": [
					{
						"name": "document_no",
						"type": "String"
					},
					{
						"name": "apply_to_doc",
						"type": "String"
					},
					{
						"name": "document_date",
						"type": "String"
					},
					{
						"name": "transaction_type",
						"type": "String"
					},
					{
						"name": "subbrandform_name",
						"type": "String"
					},
					{
						"name": "prod_name",
						"type": "String"
					},
					{
						"name": "customer_name",
						"type": "String"
					},
					{
						"name": "customer_code",
						"type": "String"
					},
					{
						"name": "channel_description",
						"type": "String"
					},
					{
						"name": "dse",
						"type": "String"
					},
					{
						"name": "pcode",
						"type": "String"
					},
					{
						"name": "customer_type",
						"type": "String"
					},
					{
						"name": "hsn_code",
						"type": "String"
					},
					{
						"name": "category",
						"type": "String"
					},
					{
						"name": "brand",
						"type": "String"
					},
					{
						"name": "brandform",
						"type": "String"
					},
					{
						"name": "quantity",
						"type": "String"
					},
					{
						"name": "gross_value",
						"type": "String"
					},
					{
						"name": "discount",
						"type": "String"
					},
					{
						"name": "taxable_scheme",
						"type": "String"
					},
					{
						"name": "cgsttax",
						"type": "String"
					},
					{
						"name": "sgsttax",
						"type": "String"
					},
					{
						"name": "igsttax",
						"type": "String"
					},
					{
						"name": "cesstax",
						"type": "String"
					},
					{
						"name": "mracc_code",
						"type": "String"
					},
					{
						"name": "mracc_desc",
						"type": "String"
					},
					{
						"name": "vendor",
						"type": "String"
					},
					{
						"name": "net_amount",
						"type": "String"
					},
					{
						"name": "tax_on_discount",
						"type": "String"
					},
					{
						"name": "tax_on_scheme",
						"type": "String"
					},
					{
						"name": "tax_in_rlp",
						"type": "String"
					},
					{
						"name": "retailing",
						"type": "String"
					},
					{
						"name": "gross_in_slp",
						"type": "String"
					},
					{
						"name": "po_no",
						"type": "String"
					},
					{
						"name": "dse_code",
						"type": "String"
					},
					{
						"name": "msu",
						"type": "String"
					},
					{
						"name": "reason",
						"type": "String"
					},
					{
						"name": "dist_gstinno",
						"type": "String"
					},
					{
						"name": "ret_gstinno",
						"type": "String"
					},
					{
						"name": "srn_ref_no",
						"type": "String"
					},
					{
						"name": "composite",
						"type": "String"
					},
					{
						"name": "cgsttax_rate",
						"type": "String"
					},
					{
						"name": "sgsttax_rate",
						"type": "String"
					},
					{
						"name": "igsttax_rate",
						"type": "String"
					},
					{
						"name": "cesstax_rate",
						"type": "String"
					},
					{
						"name": "branch_code",
						"type": "String"
					},
					{
						"name": "branch_name",
						"type": "String"
					},
					{
						"name": "order_mode",
						"type": "String"
					},
					{
						"name": "tc_code",
						"type": "String"
					},
					{
						"name": "tc_name",
						"type": "String"
					}
				]
			},
			"dependsOn": []
		},
		{
			"name": "[concat(parameters('factoryName'), '/ADLSCSVDataSource_Folder_withoutgzip')]",
			"type": "Microsoft.DataFactory/factories/datasets",
			"apiVersion": "2018-06-01",
			"properties": {
				"linkedServiceName": {
					"referenceName": "dfdatafoundationLink",
					"type": "LinkedServiceReference"
				},
				"parameters": {
					"Container": {
						"type": "string"
					},
					"Directory": {
						"type": "string"
					}
				},
				"folder": {
					"name": "OtherDataSet"
				},
				"annotations": [],
				"type": "DelimitedText",
				"typeProperties": {
					"location": {
						"type": "AzureBlobStorageLocation",
						"fileName": "DPSR_cloud01_2020Oct06.gz",
						"folderPath": {
							"value": "@dataset().Directory",
							"type": "Expression"
						},
						"container": {
							"value": "@dataset().Container",
							"type": "Expression"
						}
					},
					"columnDelimiter": ",",
					"escapeChar": "\\",
					"firstRowAsHeader": true,
					"quoteChar": "\""
				},
				"schema": [
					{
						"name": "document_no",
						"type": "String"
					},
					{
						"name": "apply_to_doc",
						"type": "String"
					},
					{
						"name": "document_date",
						"type": "String"
					},
					{
						"name": "transaction_type",
						"type": "String"
					},
					{
						"name": "subbrandform_name",
						"type": "String"
					},
					{
						"name": "prod_name",
						"type": "String"
					},
					{
						"name": "customer_name",
						"type": "String"
					},
					{
						"name": "customer_code",
						"type": "String"
					},
					{
						"name": "channel_description",
						"type": "String"
					},
					{
						"name": "dse",
						"type": "String"
					},
					{
						"name": "pcode",
						"type": "String"
					},
					{
						"name": "customer_type",
						"type": "String"
					},
					{
						"name": "hsn_code",
						"type": "String"
					},
					{
						"name": "category",
						"type": "String"
					},
					{
						"name": "brand",
						"type": "String"
					},
					{
						"name": "brandform",
						"type": "String"
					},
					{
						"name": "quantity",
						"type": "String"
					},
					{
						"name": "gross_value",
						"type": "String"
					},
					{
						"name": "discount",
						"type": "String"
					},
					{
						"name": "taxable_scheme",
						"type": "String"
					},
					{
						"name": "cgsttax",
						"type": "String"
					},
					{
						"name": "sgsttax",
						"type": "String"
					},
					{
						"name": "igsttax",
						"type": "String"
					},
					{
						"name": "cesstax",
						"type": "String"
					},
					{
						"name": "mracc_code",
						"type": "String"
					},
					{
						"name": "mracc_desc",
						"type": "String"
					},
					{
						"name": "vendor",
						"type": "String"
					},
					{
						"name": "net_amount",
						"type": "String"
					},
					{
						"name": "tax_on_discount",
						"type": "String"
					},
					{
						"name": "tax_on_scheme",
						"type": "String"
					},
					{
						"name": "tax_in_rlp",
						"type": "String"
					},
					{
						"name": "retailing",
						"type": "String"
					},
					{
						"name": "gross_in_slp",
						"type": "String"
					},
					{
						"name": "po_no",
						"type": "String"
					},
					{
						"name": "dse_code",
						"type": "String"
					},
					{
						"name": "msu",
						"type": "String"
					},
					{
						"name": "reason",
						"type": "String"
					},
					{
						"name": "dist_gstinno",
						"type": "String"
					},
					{
						"name": "ret_gstinno",
						"type": "String"
					},
					{
						"name": "srn_ref_no",
						"type": "String"
					},
					{
						"name": "composite",
						"type": "String"
					},
					{
						"name": "cgsttax_rate",
						"type": "String"
					},
					{
						"name": "sgsttax_rate",
						"type": "String"
					},
					{
						"name": "igsttax_rate",
						"type": "String"
					},
					{
						"name": "cesstax_rate",
						"type": "String"
					},
					{
						"name": "branch_code",
						"type": "String"
					},
					{
						"name": "branch_name",
						"type": "String"
					},
					{
						"name": "order_mode",
						"type": "String"
					},
					{
						"name": "tc_code",
						"type": "String"
					},
					{
						"name": "tc_name",
						"type": "String"
					}
				]
			},
			"dependsOn": []
		},
		{
			"name": "[concat(parameters('factoryName'), '/ADLSDataset')]",
			"type": "Microsoft.DataFactory/factories/datasets",
			"apiVersion": "2018-06-01",
			"properties": {
				"linkedServiceName": {
					"referenceName": "LinkedService_PnGADLS",
					"type": "LinkedServiceReference"
				},
				"parameters": {
					"folder": {
						"type": "string"
					},
					"directory": {
						"type": "string"
					}
				},
				"folder": {
					"name": "OtherDataSet"
				},
				"annotations": [],
				"type": "Binary",
				"typeProperties": {
					"location": {
						"type": "AzureBlobFSLocation",
						"folderPath": {
							"value": "@dataset().folder",
							"type": "Expression"
						},
						"fileSystem": {
							"value": "@dataset().directory",
							"type": "Expression"
						}
					},
					"compression": {
						"type": "gzip",
						"level": "Optimal"
					}
				}
			},
			"dependsOn": []
		},
		{
			"name": "[concat(parameters('factoryName'), '/ADLSDataset_Copy')]",
			"type": "Microsoft.DataFactory/factories/datasets",
			"apiVersion": "2018-06-01",
			"properties": {
				"linkedServiceName": {
					"referenceName": "dfdatafoundationLink",
					"type": "LinkedServiceReference"
				},
				"parameters": {
					"folder": {
						"type": "string"
					},
					"directory": {
						"type": "string"
					}
				},
				"folder": {
					"name": "OtherDataSet"
				},
				"annotations": [],
				"type": "Binary",
				"typeProperties": {
					"location": {
						"type": "AzureBlobStorageLocation",
						"folderPath": {
							"value": "@dataset().folder",
							"type": "Expression"
						},
						"container": {
							"value": "@dataset().directory",
							"type": "Expression"
						}
					},
					"compression": {
						"type": "gzip",
						"level": "Optimal"
					}
				}
			},
			"dependsOn": []
		},
		{
			"name": "[concat(parameters('factoryName'), '/ADLSDataset_Onefile')]",
			"type": "Microsoft.DataFactory/factories/datasets",
			"apiVersion": "2018-06-01",
			"properties": {
				"linkedServiceName": {
					"referenceName": "LinkedService_PnGADLS",
					"type": "LinkedServiceReference"
				},
				"parameters": {
					"folder": {
						"type": "string"
					},
					"directory": {
						"type": "string"
					},
					"filename": {
						"type": "string"
					}
				},
				"folder": {
					"name": "OtherDataSet"
				},
				"annotations": [],
				"type": "Binary",
				"typeProperties": {
					"location": {
						"type": "AzureBlobFSLocation",
						"fileName": {
							"value": "@dataset().filename",
							"type": "Expression"
						},
						"folderPath": {
							"value": "@dataset().folder",
							"type": "Expression"
						},
						"fileSystem": {
							"value": "@dataset().directory",
							"type": "Expression"
						}
					},
					"compression": {
						"type": "gzip",
						"level": "Optimal"
					}
				}
			},
			"dependsOn": []
		},
		{
			"name": "[concat(parameters('factoryName'), '/CSVDataSource_File_withoutGzip')]",
			"type": "Microsoft.DataFactory/factories/datasets",
			"apiVersion": "2018-06-01",
			"properties": {
				"linkedServiceName": {
					"referenceName": "dfdatafoundationLink",
					"type": "LinkedServiceReference"
				},
				"parameters": {
					"Container": {
						"type": "string"
					},
					"Directory": {
						"type": "string",
						"defaultValue": null
					},
					"Filename": {
						"type": "string"
					}
				},
				"folder": {
					"name": "OtherDataSet"
				},
				"annotations": [],
				"type": "DelimitedText",
				"typeProperties": {
					"location": {
						"type": "AzureBlobStorageLocation",
						"fileName": {
							"value": "@dataset().Filename",
							"type": "Expression"
						},
						"folderPath": {
							"value": "@dataset().Directory",
							"type": "Expression"
						},
						"container": {
							"value": "@dataset().Container",
							"type": "Expression"
						}
					},
					"columnDelimiter": ",",
					"escapeChar": "\\",
					"firstRowAsHeader": false,
					"quoteChar": "\""
				},
				"schema": [
					{
						"name": "document_no",
						"type": "String"
					},
					{
						"name": "apply_to_doc",
						"type": "String"
					},
					{
						"name": "document_date",
						"type": "String"
					},
					{
						"name": "transaction_type",
						"type": "String"
					},
					{
						"name": "subbrandform_name",
						"type": "String"
					},
					{
						"name": "prod_name",
						"type": "String"
					},
					{
						"name": "customer_name",
						"type": "String"
					},
					{
						"name": "customer_code",
						"type": "String"
					},
					{
						"name": "channel_description",
						"type": "String"
					},
					{
						"name": "dse",
						"type": "String"
					},
					{
						"name": "pcode",
						"type": "String"
					},
					{
						"name": "customer_type",
						"type": "String"
					},
					{
						"name": "hsn_code",
						"type": "String"
					},
					{
						"name": "category",
						"type": "String"
					},
					{
						"name": "brand",
						"type": "String"
					},
					{
						"name": "brandform",
						"type": "String"
					},
					{
						"name": "quantity",
						"type": "String"
					},
					{
						"name": "gross_value",
						"type": "String"
					},
					{
						"name": "discount",
						"type": "String"
					},
					{
						"name": "taxable_scheme",
						"type": "String"
					},
					{
						"name": "cgsttax",
						"type": "String"
					},
					{
						"name": "sgsttax",
						"type": "String"
					},
					{
						"name": "igsttax",
						"type": "String"
					},
					{
						"name": "cesstax",
						"type": "String"
					},
					{
						"name": "mracc_code",
						"type": "String"
					},
					{
						"name": "mracc_desc",
						"type": "String"
					},
					{
						"name": "vendor",
						"type": "String"
					},
					{
						"name": "net_amount",
						"type": "String"
					},
					{
						"name": "tax_on_discount",
						"type": "String"
					},
					{
						"name": "tax_on_scheme",
						"type": "String"
					},
					{
						"name": "tax_in_rlp",
						"type": "String"
					},
					{
						"name": "retailing",
						"type": "String"
					},
					{
						"name": "gross_in_slp",
						"type": "String"
					},
					{
						"name": "po_no",
						"type": "String"
					},
					{
						"name": "dse_code",
						"type": "String"
					},
					{
						"name": "msu",
						"type": "String"
					},
					{
						"name": "reason",
						"type": "String"
					},
					{
						"name": "dist_gstinno",
						"type": "String"
					},
					{
						"name": "ret_gstinno",
						"type": "String"
					},
					{
						"name": "srn_ref_no",
						"type": "String"
					},
					{
						"name": "composite",
						"type": "String"
					},
					{
						"name": "cgsttax_rate",
						"type": "String"
					},
					{
						"name": "sgsttax_rate",
						"type": "String"
					},
					{
						"name": "igsttax_rate",
						"type": "String"
					},
					{
						"name": "cesstax_rate",
						"type": "String"
					},
					{
						"name": "branch_code",
						"type": "String"
					},
					{
						"name": "branch_name",
						"type": "String"
					},
					{
						"name": "order_mode",
						"type": "String"
					},
					{
						"name": "tc_code",
						"type": "String"
					},
					{
						"name": "tc_name",
						"type": "String"
					}
				]
			},
			"dependsOn": []
		},
		{
			"name": "[concat(parameters('factoryName'), '/CSVDataSource_File_withoutGzip_V2')]",
			"type": "Microsoft.DataFactory/factories/datasets",
			"apiVersion": "2018-06-01",
			"properties": {
				"linkedServiceName": {
					"referenceName": "dfdatafoundationstorage",
					"type": "LinkedServiceReference"
				},
				"parameters": {
					"Container": {
						"type": "string"
					},
					"Folder": {
						"type": "string",
						"defaultValue": " "
					},
					"Filename": {
						"type": "string"
					}
				},
				"folder": {
					"name": "OtherDataSet"
				},
				"annotations": [],
				"type": "DelimitedText",
				"typeProperties": {
					"location": {
						"type": "AzureBlobStorageLocation",
						"fileName": {
							"value": "@dataset().Filename",
							"type": "Expression"
						},
						"folderPath": {
							"value": "@dataset().Folder",
							"type": "Expression"
						},
						"container": {
							"value": "@dataset().Container",
							"type": "Expression"
						}
					},
					"columnDelimiter": ",",
					"escapeChar": "\\",
					"firstRowAsHeader": true,
					"quoteChar": "\""
				},
				"schema": [
					{
						"name": "document_no",
						"type": "String"
					},
					{
						"name": "apply_to_doc",
						"type": "String"
					},
					{
						"name": "document_date",
						"type": "String"
					},
					{
						"name": "transaction_type",
						"type": "String"
					},
					{
						"name": "subbrandform_name",
						"type": "String"
					},
					{
						"name": "prod_name",
						"type": "String"
					},
					{
						"name": "customer_name",
						"type": "String"
					},
					{
						"name": "customer_code",
						"type": "String"
					},
					{
						"name": "channel_description",
						"type": "String"
					},
					{
						"name": "dse",
						"type": "String"
					},
					{
						"name": "pcode",
						"type": "String"
					},
					{
						"name": "customer_type",
						"type": "String"
					},
					{
						"name": "hsn_code",
						"type": "String"
					},
					{
						"name": "category",
						"type": "String"
					},
					{
						"name": "brand",
						"type": "String"
					},
					{
						"name": "brandform",
						"type": "String"
					},
					{
						"name": "quantity",
						"type": "String"
					},
					{
						"name": "gross_value",
						"type": "String"
					},
					{
						"name": "discount",
						"type": "String"
					},
					{
						"name": "taxable_scheme",
						"type": "String"
					},
					{
						"name": "cgsttax",
						"type": "String"
					},
					{
						"name": "sgsttax",
						"type": "String"
					},
					{
						"name": "igsttax",
						"type": "String"
					},
					{
						"name": "cesstax",
						"type": "String"
					},
					{
						"name": "mracc_code",
						"type": "String"
					},
					{
						"name": "mracc_desc",
						"type": "String"
					},
					{
						"name": "vendor",
						"type": "String"
					},
					{
						"name": "net_amount",
						"type": "String"
					},
					{
						"name": "tax_on_discount",
						"type": "String"
					},
					{
						"name": "tax_on_scheme",
						"type": "String"
					},
					{
						"name": "tax_in_rlp",
						"type": "String"
					},
					{
						"name": "retailing",
						"type": "String"
					},
					{
						"name": "gross_in_slp",
						"type": "String"
					},
					{
						"name": "po_no",
						"type": "String"
					},
					{
						"name": "dse_code",
						"type": "String"
					},
					{
						"name": "msu",
						"type": "String"
					},
					{
						"name": "reason",
						"type": "String"
					},
					{
						"name": "dist_gstinno",
						"type": "String"
					},
					{
						"name": "ret_gstinno",
						"type": "String"
					},
					{
						"name": "srn_ref_no",
						"type": "String"
					},
					{
						"name": "composite",
						"type": "String"
					},
					{
						"name": "cgsttax_rate",
						"type": "String"
					},
					{
						"name": "sgsttax_rate",
						"type": "String"
					},
					{
						"name": "igsttax_rate",
						"type": "String"
					},
					{
						"name": "cesstax_rate",
						"type": "String"
					},
					{
						"name": "branch_code",
						"type": "String"
					},
					{
						"name": "branch_name",
						"type": "String"
					},
					{
						"name": "order_mode",
						"type": "String"
					},
					{
						"name": "tc_code",
						"type": "String"
					},
					{
						"name": "tc_name",
						"type": "String"
					}
				]
			},
			"dependsOn": []
		},
		{
			"name": "[concat(parameters('factoryName'), '/CSVDataSource_File_withoutGzip_V2_pipe')]",
			"type": "Microsoft.DataFactory/factories/datasets",
			"apiVersion": "2018-06-01",
			"properties": {
				"linkedServiceName": {
					"referenceName": "dfdatafoundationstorage",
					"type": "LinkedServiceReference"
				},
				"parameters": {
					"Container": {
						"type": "string"
					},
					"Folder": {
						"type": "string",
						"defaultValue": " "
					},
					"Filename": {
						"type": "string"
					}
				},
				"folder": {
					"name": "OtherDataSet"
				},
				"annotations": [],
				"type": "DelimitedText",
				"typeProperties": {
					"location": {
						"type": "AzureBlobStorageLocation",
						"fileName": {
							"value": "@dataset().Filename",
							"type": "Expression"
						},
						"folderPath": {
							"value": "@dataset().Folder",
							"type": "Expression"
						},
						"container": {
							"value": "@dataset().Container",
							"type": "Expression"
						}
					},
					"columnDelimiter": "|",
					"escapeChar": "\\",
					"firstRowAsHeader": true,
					"quoteChar": "\""
				},
				"schema": [
					{
						"name": "document_no",
						"type": "String"
					},
					{
						"name": "apply_to_doc",
						"type": "String"
					},
					{
						"name": "document_date",
						"type": "String"
					},
					{
						"name": "transaction_type",
						"type": "String"
					},
					{
						"name": "subbrandform_name",
						"type": "String"
					},
					{
						"name": "prod_name",
						"type": "String"
					},
					{
						"name": "customer_name",
						"type": "String"
					},
					{
						"name": "customer_code",
						"type": "String"
					},
					{
						"name": "channel_description",
						"type": "String"
					},
					{
						"name": "dse",
						"type": "String"
					},
					{
						"name": "pcode",
						"type": "String"
					},
					{
						"name": "customer_type",
						"type": "String"
					},
					{
						"name": "hsn_code",
						"type": "String"
					},
					{
						"name": "category",
						"type": "String"
					},
					{
						"name": "brand",
						"type": "String"
					},
					{
						"name": "brandform",
						"type": "String"
					},
					{
						"name": "quantity",
						"type": "String"
					},
					{
						"name": "gross_value",
						"type": "String"
					},
					{
						"name": "discount",
						"type": "String"
					},
					{
						"name": "taxable_scheme",
						"type": "String"
					},
					{
						"name": "cgsttax",
						"type": "String"
					},
					{
						"name": "sgsttax",
						"type": "String"
					},
					{
						"name": "igsttax",
						"type": "String"
					},
					{
						"name": "cesstax",
						"type": "String"
					},
					{
						"name": "mracc_code",
						"type": "String"
					},
					{
						"name": "mracc_desc",
						"type": "String"
					},
					{
						"name": "vendor",
						"type": "String"
					},
					{
						"name": "net_amount",
						"type": "String"
					},
					{
						"name": "tax_on_discount",
						"type": "String"
					},
					{
						"name": "tax_on_scheme",
						"type": "String"
					},
					{
						"name": "tax_in_rlp",
						"type": "String"
					},
					{
						"name": "retailing",
						"type": "String"
					},
					{
						"name": "gross_in_slp",
						"type": "String"
					},
					{
						"name": "po_no",
						"type": "String"
					},
					{
						"name": "dse_code",
						"type": "String"
					},
					{
						"name": "msu",
						"type": "String"
					},
					{
						"name": "reason",
						"type": "String"
					},
					{
						"name": "dist_gstinno",
						"type": "String"
					},
					{
						"name": "ret_gstinno",
						"type": "String"
					},
					{
						"name": "srn_ref_no",
						"type": "String"
					},
					{
						"name": "composite",
						"type": "String"
					},
					{
						"name": "cgsttax_rate",
						"type": "String"
					},
					{
						"name": "sgsttax_rate",
						"type": "String"
					},
					{
						"name": "igsttax_rate",
						"type": "String"
					},
					{
						"name": "cesstax_rate",
						"type": "String"
					},
					{
						"name": "branch_code",
						"type": "String"
					},
					{
						"name": "branch_name",
						"type": "String"
					},
					{
						"name": "order_mode",
						"type": "String"
					},
					{
						"name": "tc_code",
						"type": "String"
					},
					{
						"name": "tc_name",
						"type": "String"
					}
				]
			},
			"dependsOn": []
		},
		{
			"name": "[concat(parameters('factoryName'), '/CustomerCSV')]",
			"type": "Microsoft.DataFactory/factories/datasets",
			"apiVersion": "2018-06-01",
			"properties": {
				"linkedServiceName": {
					"referenceName": "dfdatafoundationLink",
					"type": "LinkedServiceReference"
				},
				"annotations": [],
				"type": "DelimitedText",
				"typeProperties": {
					"location": {
						"type": "AzureBlobStorageLocation",
						"fileName": "ncsRetailer.csv",
						"container": "test"
					},
					"columnDelimiter": ",",
					"escapeChar": "\\",
					"firstRowAsHeader": true,
					"quoteChar": "\""
				},
				"schema": [
					{
						"name": "SUBDCODE",
						"type": "String"
					},
					{
						"name": "CUSTCODE",
						"type": "String"
					},
					{
						"name": "CUSTNAME",
						"type": "String"
					},
					{
						"name": "CHANNEL",
						"type": "String"
					},
					{
						"name": "DSE",
						"type": "String"
					},
					{
						"name": "CUSTTYPE",
						"type": "String"
					},
					{
						"name": "TOWN",
						"type": "String"
					},
					{
						"name": "TOWNCLASS",
						"type": "String"
					},
					{
						"name": "AREA",
						"type": "String"
					},
					{
						"name": "COVERAGESTS",
						"type": "String"
					},
					{
						"name": "DATE",
						"type": "String"
					},
					{
						"name": "SELECTEDDATE",
						"type": "String"
					},
					{
						"name": "CUSTCLASS",
						"type": "String"
					},
					{
						"name": "STATUS",
						"type": "String"
					},
					{
						"name": "MRAccCde",
						"type": "String"
					},
					{
						"name": "DSECode",
						"type": "String"
					},
					{
						"name": "Latitude",
						"type": "String"
					},
					{
						"name": "Longitude",
						"type": "String"
					}
				]
			},
			"dependsOn": []
		}
	]
}